airzone_mqtt/__init__.py
airzone_mqtt/common.py
airzone_mqtt/const.py
airzone_mqtt/device.py
airzone_mqtt/exceptions.py
airzone_mqtt/mqttapi.py
airzone_mqtt/py.typed
airzone_mqtt/system.py
airzone_mqtt/update.py
airzone_mqtt/zone.py
airzone_mqtt-0.0.4.dist-info/licenses/LICENSE
airzone_mqtt-0.0.4.dist-info/METADATA
airzone_mqtt-0.0.4.dist-info/WHEEL
airzone_mqtt-0.0.4.dist-info/top_level.txt
airzone_mqtt-0.0.4.dist-info/RECORD
