Metadata-Version: 2.4
Name: airzone-mqtt
Version: 0.0.4
Summary: Library to control Airzone MQTT devices
Author-email: Álvaro Fernández Rojas <noltari@gmail.com>
License-Expression: Apache-2.0
Project-URL: Homepage, https://github.com/Noltari/airzone-mqtt
Project-URL: Bug Tracker, https://github.com/Noltari/airzone-mqtt/issues
Keywords: airzone,hvac,home,mqtt
Platform: any
Classifier: Development Status :: 4 - Beta
Classifier: Intended Audience :: Developers
Classifier: Natural Language :: English
Classifier: Programming Language :: Python :: 3
Classifier: Programming Language :: Python :: 3.12
Classifier: Programming Language :: Python :: 3.13
Classifier: Topic :: Home Automation
Requires-Python: >=3.12
License-File: LICENSE
Dynamic: license-file
